DESCRIPTION.rst
MANIFEST.in
setup.py
jycat/__init__.py
jycat/jycat.py
jycat.egg-info/PKG-INFO
jycat.egg-info/SOURCES.txt
jycat.egg-info/dependency_links.txt
jycat.egg-info/entry_points.txt
jycat.egg-info/requires.txt
jycat.egg-info/top_level.txt